{
    "id_card": [
        {
            "id_num": {
                "bbox": {
                    "x1": 1100,
                    "y1": 20,
                    "x2": 1390,
                    "y2": 66
                },
                "text": "307837243"
            }
        },
        {
            "khm_name": {
                "bbox": {
                    "x1": 400,
                    "y1": 110,
                    "x2": 1043,
                    "y2": 181
                },
                "text": "គោត្តនាមនិងនាម: រូបស្បាតម កញ្ជះវិលវង់"
            }
        },
        {
            "eng_name": {
                "bbox": {
                    "x1": 600,
                    "y1": 190,
                    "x2": 908,
                    "y2": 237
                },
                "text": "HOMOD POLYPE"
            }
        },
        {
            "dob": {
                "bbox": {
                    "x1": 400,
                    "y1": 260,
                    "x2": 1243,
                    "y2": 332
                },
                "text": "ថ្ងៃខែឆ្នាំកំណើត: ០៣.០៦.១៩៨៧ ភេទ: ស្រី កំពស់: ១៥៦"
            }
        },
        {
            "pob": {
                "bbox": {
                    "x1": 400,
                    "y1": 340,
                    "x2": 1282,
                    "y2": 413
                },
                "text": "ទីកន្លែងកំណើត: ឃុំកំពង់ត្របែក ស្រុកសៀមរាប សៀមរាប"
            }
        },
        {
            "address_1": {
                "bbox": {
                    "x1": 400,
                    "y1": 410,
                    "x2": 756,
                    "y2": 483
                },
                "text": "អាសយដ្ឋាន: ភូមិជ្រៃថ្មី"
            }
        },
        {
            "address_2": {
                "bbox": {
                    "x1": 400,
                    "y1": 480,
                    "x2": 963,
                    "y2": 552
                },
                "text": "ឃុំទំនប់ដាច់ ក្រុងស្វាយរៀង កណ្ដាល"
            }
        },
        {
            "issue_expire_date": {
                "bbox": {
                    "x1": 400,
                    "y1": 550,
                    "x2": 1156,
                    "y2": 619
                },
                "text": "សុពលភាព: ០៣.០៨.១៩៦៧ ដល់ថ្ងៃ ០៩.១២.២០០៥"
            }
        },
        {
            "identify": {
                "bbox": {
                    "x1": 400,
                    "y1": 620,
                    "x2": 835,
                    "y2": 691
                },
                "text": "ភិនភាគ: ប្រច្រុយចុងភ្នែកស្តាំ"
            }
        },
        {
            "mrz_1": {
                "bbox": {
                    "x1": 50,
                    "y1": 700,
                    "x2": 1420,
                    "y2": 775
                },
                "text": "IDKHM401156256<<<<<<<<<<<<<<<<"
            }
        },
        {
            "mrz_2": {
                "bbox": {
                    "x1": 50,
                    "y1": 800,
                    "x2": 1420,
                    "y2": 875
                },
                "text": "2425812F6KHM<<<<<<<<<<<<<<<<<6"
            }
        },
        {
            "mrz_3": {
                "bbox": {
                    "x1": 50,
                    "y1": 900,
                    "x2": 1465,
                    "y2": 970
                },
                "text": "SOG<<CPF<<<<<<<<<<<<<<<<<<<<<<<"
            }
        }
    ]
}